{"Id":"47855","ProductId":"B004SRH2B6","UserId":"AF9VU4OP3UQN7","ProfileName":"anon","HelpfulnessNumerator":1,"HelpfulnessDenominator":1,"Score":1,"date":"2010-08-23","Summary":"used to be great...not any longer.","text":"frankly i don't care about the packaging, (some folks are up in arms about the new plastic bottles rather than the old tetra packs) but zico--which used to be my favorite coco water--no longer tastes as good as it once did. then i read that it's now FROM CONCENTRATE rather than being what it once was, and i don't see any reason to purchase it any longer. very disappointed."}
