{"Id":"21035","ProductId":"B002QWP89S","UserId":"A20L2URGVM0U3O","ProfileName":"J. Phillips","HelpfulnessNumerator":0,"HelpfulnessDenominator":0,"Score":5,"date":"2012-10-12","Summary":"OUR DOGS LOVE THEM","text":"Our Chussel's Love these toothbrush treats. When I ask them if they want to brush their teeth, they jump a mile high to get them. It dosent help their breath to to much, but I know its keeping their teeth clean. Also these are a little on the expensive side almost everywhere, Amazon has the best price. Thanks Amazon."}
