{"Id":"9700","ProductId":"B001LXYA5Q","UserId":"A2J1LWMV1VZBE3","ProfileName":"Matthew Moore \"Mmoore\"","HelpfulnessNumerator":3,"HelpfulnessDenominator":4,"Score":5,"date":"2009-01-19","Summary":"They Actually Work!!!","Text":"At first i did not think they would work, but i bought them after reading the scientific view of them and then decided to buy them just to see. After i got them i had to try something sour just to see, so i took a half tablet and put some lemon juice on my tung. Amazingly they worked!!! This is an awesome product for anyone who likes wired things or just has a liking of chemistry. :)"}
