{"Id":"399831","ProductId":"B002IEVJRY","UserId":"A1JBBR4MNGQ70G","ProfileName":"Falkor The White Luck Dragon","HelpfulnessNumerator":0,"HelpfulnessDenominator":0,"Score":4,"date":"2012-06-04","Summary":"Just Add Ice Cubes For A Delicious Summer Coffee Drink","text":"This cappucino has just the right combination of good quality coffee and cocoa.  It makes a refreshing delicious slightly decadant drink when poured over ice cubes.  Great for someone who loves both coffee and chocolate and so convenient right out of the can."}
