{"Id":"47880","ProductId":"B004SRH2B6","UserId":"A1KVMHIX6JS4LP","ProfileName":"Franz Wallace \"D wallace\"","HelpfulnessNumerator":2,"HelpfulnessDenominator":3,"Score":1,"date":"2010-10-11","Summary":"nasty","text":"I am from Jamaica, and I had coconuts straight from the trees and this does not taste natural at all, as a matter of fact this is the worst tasting coconut water I have ever tasted.  I was very disappointed, Zico does not come close. I have to give VITA COCO FIVE STAR and this None."}
